aioynab/_version.py
aioynab/client.py
aioynab-0.1.2.dist-info/LICENSE
aioynab-0.1.2.dist-info/METADATA
aioynab-0.1.2.dist-info/WHEEL
aioynab-0.1.2.dist-info/top_level.txt
aioynab-0.1.2.dist-info/RECORD
