Metadata-Version: 2.1
Name: aioynab
Version: 0.1.2
Summary: This module provides a YNAB API client implemented using python 3 asyncio.
Home-page: https://github.com/boralyl/aioynab
Author: Aaron Godfrey
License: MIT
Keywords: python,ynab,asyncio
Platform: UNKNOWN
Classifier: Intended Audience :: Developers
Classifier: License :: OSI Approved :: MIT License
Classifier: Operating System :: OS Independent
Classifier: Programming Language :: Python :: 3
Classifier: Programming Language :: Python :: 3.5
Classifier: Programming Language :: Python :: 3.6
Classifier: Programming Language :: Python :: 3.7
Requires-Dist: aiohttp (<4.0.0,>=3.0.0)
Provides-Extra: docs
Requires-Dist: sphinx (<2.0.0,>=1.5.4) ; extra == 'docs'
Requires-Dist: sphinx-autodoc-typehints (<2.0.0,>=1.2.4) ; extra == 'docs'
Requires-Dist: sphinx-rtd-theme (<1.0.0,>=0.2.4) ; extra == 'docs'
Requires-Dist: sphinxcontrib-httpdomain (<2.0.0,>=1.5.0) ; extra == 'docs'
Provides-Extra: tests
Requires-Dist: aioresponses ; extra == 'tests'
Requires-Dist: codecov ; extra == 'tests'
Requires-Dist: coverage (<5.0.0,>=4.4.1) ; extra == 'tests'
Requires-Dist: flake8 (<4.0.0,>=3.3.0) ; extra == 'tests'
Requires-Dist: pytest (<5.0.0,>=4.0.0) ; extra == 'tests'
